Metadata-Version: 2.1
Name: PromptInput
Version: 0.7
Summary: A python library build over argument parser to prompt user for input.
Home-page: https://github.com/shadrul/PromptInput
Author: Shadrul
Author-email: shadrul100@gmail.com
License: MIT
Download-URL: https://github.com/shadrul/PromptInput/archive/refs/tags/version-0.5.tar.gz
Keywords: Argument parser,Prompt Input
Platform: UNKNOWN
Classifier: Development Status :: 3 - Alpha
Classifier: Intended Audience :: Developers
Classifier: Topic :: Software Development :: Build Tools
Classifier: License :: OSI Approved :: MIT License
Classifier: Programming Language :: Python :: 3
Classifier: Programming Language :: Python :: 3.4
Classifier: Programming Language :: Python :: 3.5
Classifier: Programming Language :: Python :: 3.6
